Metadata-Version: 2.4
Name: investimentpy-isabelapt
Version: 1.0.1
Summary: Uma biblioteca para análise de investimentos
Home-page: https://github.com/tadrianonet/investimentpy
Author: Thiago S Adriano
Author-email: prof.thiagoadriano@gmail.com
License: MIT
Dynamic: author
Dynamic: author-email
Dynamic: description
Dynamic: description-content-type
Dynamic: home-page
Dynamic: license
Dynamic: summary
